{"title": "самолёт", "tags": ["airplane"], "items": [{"tag": "airplane", "path": "/brasil/2007-02-27", "place": "brasil", "date": "2007-02-27", "type": "episode", "title": "Отлёт", "descr": "Наш самолёт готовят под посадку", "episode": 2, "photo": "DSCN7132.JPG"}, {"tag": "airplane", "path": "/brasil/2007-02-28", "place": "brasil", "date": "2007-02-28", "type": "episode", "title": "Сан-Паулу", "descr": "Загружают багаж в наш самолёт, которым мы полетим в Белу-Оризонти. Пилот открыл окошко проветрить в кабине.", "episode": 14, "photo": "DSCN7175.JPG"}, {"tag": "airplane", "path": "/brasil/2007-04-29", "place": "brasil", "date": "2007-04-29", "type": "episode", "title": "Rio III (Corcovado)", "descr": "Самолётик тащит по небу какой-то лозунг: «Bienvenue aux agents»", "episode": 1, "photo": "DSCN8656.JPG"}]}